openproject/__init__.py
openproject/client.py
openproject/constants.py
openproject/exceptions.py
openproject/types.py
openproject-0.6.0.dist-info/LICENSE
openproject-0.6.0.dist-info/METADATA
openproject-0.6.0.dist-info/WHEEL
openproject-0.6.0.dist-info/RECORD
