Metadata-Version: 2.1
Name: openproject
Version: 0.6.0
Summary: Python SDK for the OpenProject API
License: MIT
Author: LOGIC
Author-email: hey@withlogic.co
Requires-Python: >=3.11,<4.0
Classifier: License :: OSI Approved :: MIT License
Classifier: Programming Language :: Python :: 3
Classifier: Programming Language :: Python :: 3.11
Requires-Dist: httpx (>=0.25.0,<0.26.0)
